termicol/__init__.py
termicol/termicol.py
idev_termicol-1.0.2.dist-info/LICENSE
idev_termicol-1.0.2.dist-info/METADATA
idev_termicol-1.0.2.dist-info/WHEEL
idev_termicol-1.0.2.dist-info/top_level.txt
idev_termicol-1.0.2.dist-info/RECORD
