Metadata-Version: 2.1
Name: idev-termicol
Version: 1.0.2
Summary: A python Simple python function aimed to handle printing of colored and / or decorated text to console / terminal.
Home-page: https://github.com/irtsa-dev/termicol
Author: IrtsaDevelopment
Author-email: Irtsa <irtsa.development@gmail.com>
Project-URL: Homepage, https://github.com/irtsa-dev/termicol
Project-URL: Bug Tracker, https://github.com/irtsa-dev/termicol/issues
Classifier: Programming Language :: Python :: 3
Classifier: License :: OSI Approved :: MIT License
Classifier: Operating System :: OS Independent
Requires-Python: >=3.6
License-File: LICENSE
